{
  "language": "ru",
  "version": 1,
  "verbs": [
    {
      "id": "ru_govorit",
      "rank": 1,
      "lemma": "говорить",
      "morph": {
        "aspect": "imperfective",
        "pair": "ru_skazat",
        "sem": "speech"
      },
      "forms": {
        "present": {
          "1sg": "говорю",
          "2sg": "говоришь",
          "3sg": "говорит",
          "1pl": "говорим",
          "2pl": "говорите",
          "3pl": "говорят"
        },
        "past": {
          "m": "говорил",
          "f": "говорила",
          "n": "говорило",
          "pl": "говорили"
        },
        "imperative": {
          "sg": "говори",
          "pl": "говорите"
        }
      },
      "examples": [
        {
          "dst": "Я говорю тихо."
        },
        {
          "dst": "Он говорил с учителем."
        },
        {
          "dst": "Она говорила с подругой."
        },
        {
          "dst": "Эхо говорило в пустой комнате."
        },
        {
          "dst": "Мы говорили об этом вчера."
        },
        {
          "dst": "Я буду говорить с ним завтра."
        },
        {
          "dst": "Говори громче."
        }
      ]
    },
    {
      "id": "ru_skazat",
      "rank": 2,
      "lemma": "сказать",
      "morph": {
        "aspect": "perfective",
        "pair": "ru_govorit",
        "sem": "speech"
      },
      "forms": {
        "present": {
          "1sg": "скажу",
          "2sg": "скажешь",
          "3sg": "скажет",
          "1pl": "скажем",
          "2pl": "скажете",
          "3pl": "скажут"
        },
        "past": {
          "m": "сказал",
          "f": "сказала",
          "n": "сказало",
          "pl": "сказали"
        },
        "imperative": {
          "sg": "скажи",
          "pl": "скажите"
        }
      },
      "examples": [
        {
          "dst": "Я скажу правду."
        },
        {
          "dst": "Он сказал это вчера."
        },
        {
          "dst": "Она сказала это тихо."
        },
        {
          "dst": "Эхо сказало одно слово."
        },
        {
          "dst": "Мы сказали об этом вчера."
        },
        {
          "dst": "Скажи это громче."
        }
      ]
    },
    {
      "id": "ru_delat",
      "rank": 3,
      "lemma": "делать",
      "morph": {
        "aspect": "imperfective",
        "pair": "ru_sdelat",
        "sem": "action"
      },
      "forms": {
        "present": {
          "1sg": "делаю",
          "2sg": "делаешь",
          "3sg": "делает",
          "1pl": "делаем",
          "2pl": "делаете",
          "3pl": "делают"
        },
        "past": {
          "m": "делал",
          "f": "делала",
          "n": "делало",
          "pl": "делали"
        },
        "imperative": {
          "sg": "делай",
          "pl": "делайте"
        }
      },
      "examples": [
        {
          "dst": "Я делаю домашнее задание."
        },
        {
          "dst": "Он делал это вчера."
        },
        {
          "dst": "Она делала работу утром."
        },
        {
          "dst": "Это делало комнату уютнее."
        },
        {
          "dst": "Мы делали это вместе."
        },
        {
          "dst": "Я буду делать это вечером."
        },
        {
          "dst": "Делай аккуратно."
        }
      ]
    },
    {
      "id": "ru_sdelat",
      "rank": 4,
      "lemma": "сделать",
      "morph": {
        "aspect": "perfective",
        "pair": "ru_delat",
        "sem": "action"
      },
      "forms": {
        "present": {
          "1sg": "сделаю",
          "2sg": "сделаешь",
          "3sg": "сделает",
          "1pl": "сделаем",
          "2pl": "сделаете",
          "3pl": "сделают"
        },
        "past": {
          "m": "сделал",
          "f": "сделала",
          "n": "сделало",
          "pl": "сделали"
        },
        "imperative": {
          "sg": "сделай",
          "pl": "сделайте"
        }
      },
      "examples": [
        {
          "dst": "Я сделаю это вечером."
        },
        {
          "dst": "Он сделал это вчера."
        },
        {
          "dst": "Она сделала работу утром."
        },
        {
          "dst": "Это сделало комнату уютнее."
        },
        {
          "dst": "Мы сделали это вместе."
        },
        {
          "dst": "Сделай это аккуратно."
        }
      ]
    },
    {
      "id": "ru_idti",
      "rank": 5,
      "lemma": "идти",
      "morph": {
        "aspect": "imperfective",
        "pair": "ru_poyti",
        "sem": "motion"
      },
      "forms": {
        "present": {
          "1sg": "иду",
          "2sg": "идёшь",
          "3sg": "идёт",
          "1pl": "идём",
          "2pl": "идёте",
          "3pl": "идут"
        },
        "past": {
          "m": "шёл",
          "f": "шла",
          "n": "шло",
          "pl": "шли"
        },
        "imperative": {
          "sg": "иди",
          "pl": "идите"
        }
      },
      "examples": [
        {
          "dst": "Я иду домой."
        },
        {
          "dst": "Он шёл по дороге."
        },
        {
          "dst": "Она шла медленно."
        },
        {
          "dst": "Привидение шло по коридору."
        },
        {
          "dst": "Мы шли вместе."
        },
        {
          "dst": "Я буду идти домой пешком."
        },
        {
          "dst": "Иди быстрее."
        }
      ]
    },
    {
      "id": "ru_poyti",
      "rank": 6,
      "lemma": "пойти",
      "morph": {
        "aspect": "perfective",
        "pair": "ru_idti",
        "sem": "motion"
      },
      "forms": {
        "present": {
          "1sg": "пойду",
          "2sg": "пойдёшь",
          "3sg": "пойдёт",
          "1pl": "пойдём",
          "2pl": "пойдёте",
          "3pl": "пойдут"
        },
        "past": {
          "m": "пошёл",
          "f": "пошла",
          "n": "пошло",
          "pl": "пошли"
        },
        "imperative": {
          "sg": "пойди",
          "pl": "пойдите"
        }
      },
      "examples": [
        {
          "dst": "Я пойду домой вечером."
        },
        {
          "dst": "Он пошёл в школу."
        },
        {
          "dst": "Она пошла в магазин."
        },
        {
          "dst": "Привидение пошло к двери."
        },
        {
          "dst": "Мы пошли домой."
        },
        {
          "dst": "Пойди скорее."
        }
      ]
    },
    {
      "id": "ru_videt",
      "rank": 7,
      "lemma": "видеть",
      "morph": {
        "aspect": "imperfective",
        "pair": "ru_uvidet",
        "sem": "mental"
      },
      "forms": {
        "present": {
          "1sg": "вижу",
          "2sg": "видишь",
          "3sg": "видит",
          "1pl": "видим",
          "2pl": "видите",
          "3pl": "видят"
        },
        "past": {
          "m": "видел",
          "f": "видела",
          "n": "видело",
          "pl": "видели"
        },
        "imperative": {}
      },
      "examples": [
        {
          "dst": "Я вижу дом."
        },
        {
          "dst": "Он видел море."
        },
        {
          "dst": "Она видела письмо."
        },
        {
          "dst": "Животное видело озеро издалека."
        },
        {
          "dst": "Мы видели это вчера."
        },
        {
          "dst": "Я буду видеть его каждый день."
        }
      ]
    },
    {
      "id": "ru_uvidet",
      "rank": 8,
      "lemma": "увидеть",
      "morph": {
        "aspect": "perfective",
        "pair": "ru_videt",
        "sem": "mental"
      },
      "forms": {
        "present": {
          "1sg": "увижу",
          "2sg": "увидишь",
          "3sg": "увидит",
          "1pl": "увидим",
          "2pl": "увидите",
          "3pl": "увидят"
        },
        "past": {
          "m": "увидел",
          "f": "увидела",
          "n": "увидело",
          "pl": "увидели"
        },
        "imperative": {
          "sg": "увидь",
          "pl": "увидьте"
        }
      },
      "examples": [
        {
          "dst": "Я увижу его завтра."
        },
        {
          "dst": "Он увидел море."
        },
        {
          "dst": "Она увидела письмо на столе."
        },
        {
          "dst": "Привидение увидело свет в окне."
        },
        {
          "dst": "Мы увидели это вчера."
        },
        {
          "dst": "Увидь это своими глазами."
        }
      ]
    },
    {
      "id": "ru_znat",
      "rank": 9,
      "lemma": "знать",
      "morph": {
        "aspect": "imperfective",
        "pair": "ru_uznat",
        "sem": "mental"
      },
      "forms": {
        "present": {
          "1sg": "знаю",
          "2sg": "знаешь",
          "3sg": "знает",
          "1pl": "знаем",
          "2pl": "знаете",
          "3pl": "знают"
        },
        "past": {
          "m": "знал",
          "f": "знала",
          "n": "знало",
          "pl": "знали"
        },
        "imperative": {
          "sg": "знай",
          "pl": "знайте"
        }
      },
      "examples": [
        {
          "dst": "Я знаю ответ."
        },
        {
          "dst": "Он знал об этом."
        },
        {
          "dst": "Она знала дорогу."
        },
        {
          "dst": "Это поколение знало цену таким словам."
        },
        {
          "dst": "Мы знали об этом вчера."
        },
        {
          "dst": "Я буду знать результат завтра."
        },
        {
          "dst": "Знай это."
        }
      ]
    },
    {
      "id": "ru_uznat",
      "rank": 10,
      "lemma": "узнать",
      "morph": {
        "aspect": "perfective",
        "pair": "ru_znat",
        "sem": "mental"
      },
      "forms": {
        "present": {
          "1sg": "узнаю",
          "2sg": "узнаешь",
          "3sg": "узнает",
          "1pl": "узнаем",
          "2pl": "узнаете",
          "3pl": "узнают"
        },
        "past": {
          "m": "узнал",
          "f": "узнала",
          "n": "узнало",
          "pl": "узнали"
        },
        "imperative": {
          "sg": "узнай",
          "pl": "узнайте"
        }
      },
      "examples": [
        {
          "dst": "Я узнаю результат завтра."
        },
        {
          "dst": "Он узнал об этом вчера."
        },
        {
          "dst": "Она узнала адрес утром."
        },
        {
          "dst": "Привидение сразу узнало знакомый голос."
        },
        {
          "dst": "Мы узнали правду позже."
        },
        {
          "dst": "Узнай подробности."
        }
      ]
    },
    {
      "id": "ru_dumat",
      "rank": 11,
      "lemma": "думать",
      "morph": {
        "aspect": "imperfective",
        "pair": "ru_podumat",
        "sem": "mental"
      },
      "forms": {
        "present": {
          "1sg": "думаю",
          "2sg": "думаешь",
          "3sg": "думает",
          "1pl": "думаем",
          "2pl": "думаете",
          "3pl": "думают"
        },
        "past": {
          "m": "думал",
          "f": "думала",
          "n": "думало",
          "pl": "думали"
        },
        "imperative": {
          "sg": "думай",
          "pl": "думайте"
        }
      },
      "examples": [
        {
          "dst": "Я думаю об этом."
        },
        {
          "dst": "Он думал о работе."
        },
        {
          "dst": "Она думала о поездке."
        },
        {
          "dst": "Общество редко думало о последствиях."
        },
        {
          "dst": "Мы думали об этом вчера."
        },
        {
          "dst": "Я буду думать об этом вечером."
        },
        {
          "dst": "Думай спокойно."
        }
      ]
    },
    {
      "id": "ru_podumat",
      "rank": 12,
      "lemma": "подумать",
      "morph": {
        "aspect": "perfective",
        "pair": "ru_dumat",
        "sem": "mental"
      },
      "forms": {
        "present": {
          "1sg": "подумаю",
          "2sg": "подумаешь",
          "3sg": "подумает",
          "1pl": "подумаем",
          "2pl": "подумаете",
          "3pl": "подумают"
        },
        "past": {
          "m": "подумал",
          "f": "подумала",
          "n": "подумало",
          "pl": "подумали"
        },
        "imperative": {
          "sg": "подумай",
          "pl": "подумайте"
        }
      },
      "examples": [
        {
          "dst": "Я подумаю об этом завтра."
        },
        {
          "dst": "Он подумал о работе."
        },
        {
          "dst": "Она подумала о письме."
        },
        {
          "dst": "Общество не подумало о таком."
        },
        {
          "dst": "Мы подумали и согласились."
        },
        {
          "dst": "Подумай ещё раз."
        }
      ]
    },
    {
      "id": "ru_brat",
      "rank": 13,
      "lemma": "брать",
      "morph": {
        "aspect": "imperfective",
        "pair": "ru_vzyat",
        "sem": "action"
      },
      "forms": {
        "present": {
          "1sg": "беру",
          "2sg": "берёшь",
          "3sg": "берёт",
          "1pl": "берём",
          "2pl": "берёте",
          "3pl": "берут"
        },
        "past": {
          "m": "брал",
          "f": "брала",
          "n": "брало",
          "pl": "брали"
        },
        "imperative": {
          "sg": "бери",
          "pl": "берите"
        }
      },
      "examples": [
        {
          "dst": "Я беру книгу."
        },
        {
          "dst": "Он брал зонт утром."
        },
        {
          "dst": "Она брала ключ со стола."
        },
        {
          "dst": "Это поколение брало власть в свои руки."
        },
        {
          "dst": "Мы брали билеты заранее."
        },
        {
          "dst": "Я буду брать обед с собой."
        },
        {
          "dst": "Бери эту книгу."
        }
      ]
    },
    {
      "id": "ru_vzyat",
      "rank": 14,
      "lemma": "взять",
      "morph": {
        "aspect": "perfective",
        "pair": "ru_brat",
        "sem": "action"
      },
      "forms": {
        "present": {
          "1sg": "возьму",
          "2sg": "возьмёшь",
          "3sg": "возьмёт",
          "1pl": "возьмём",
          "2pl": "возьмёте",
          "3pl": "возьмут"
        },
        "past": {
          "m": "взял",
          "f": "взяла",
          "n": "взяло",
          "pl": "взяли"
        },
        "imperative": {
          "sg": "возьми",
          "pl": "возьмите"
        }
      },
      "examples": [
        {
          "dst": "Я возьму книгу завтра."
        },
        {
          "dst": "Он взял зонт утром."
        },
        {
          "dst": "Она взяла ключ со стола."
        },
        {
          "dst": "Это поколение взяло власть в свои руки."
        },
        {
          "dst": "Мы взяли билеты заранее."
        },
        {
          "dst": "Возьми эту книгу."
        }
      ]
    },
    {
      "id": "ru_davat",
      "rank": 15,
      "lemma": "давать",
      "morph": {
        "aspect": "imperfective",
        "pair": "ru_dat",
        "sem": "action"
      },
      "forms": {
        "present": {
          "1sg": "даю",
          "2sg": "даёшь",
          "3sg": "даёт",
          "1pl": "даём",
          "2pl": "даёте",
          "3pl": "дают"
        },
        "past": {
          "m": "давал",
          "f": "давала",
          "n": "давало",
          "pl": "давали"
        },
        "imperative": {
          "sg": "давай",
          "pl": "давайте"
        }
      },
      "examples": [
        {
          "dst": "Я даю тебе книгу."
        },
        {
          "dst": "Он давал мне совет."
        },
        {
          "dst": "Она давала ребёнку воду."
        },
        {
          "dst": "Это давало нам надежду."
        },
        {
          "dst": "Мы давали ему время."
        },
        {
          "dst": "Я буду давать тебе новости."
        },
        {
          "dst": "Давай мне знать."
        }
      ]
    },
    {
      "id": "ru_dat",
      "rank": 16,
      "lemma": "дать",
      "morph": {
        "aspect": "perfective",
        "pair": "ru_davat",
        "sem": "action"
      },
      "forms": {
        "present": {
          "1sg": "дам",
          "2sg": "дашь",
          "3sg": "даст",
          "1pl": "дадим",
          "2pl": "дадите",
          "3pl": "дадут"
        },
        "past": {
          "m": "дал",
          "f": "дала",
          "n": "дало",
          "pl": "дали"
        },
        "imperative": {
          "sg": "дай",
          "pl": "дайте"
        }
      },
      "examples": [
        {
          "dst": "Я дам тебе книгу завтра."
        },
        {
          "dst": "Он дал мне совет."
        },
        {
          "dst": "Она дала ребёнку воду."
        },
        {
          "dst": "Это дало нам надежду."
        },
        {
          "dst": "Мы дали ему время."
        },
        {
          "dst": "Дай мне знать."
        }
      ]
    },
    {
      "id": "ru_pisat",
      "rank": 17,
      "lemma": "писать",
      "morph": {
        "aspect": "imperfective",
        "pair": "ru_napisat",
        "sem": "action"
      },
      "forms": {
        "present": {
          "1sg": "пишу",
          "2sg": "пишешь",
          "3sg": "пишет",
          "1pl": "пишем",
          "2pl": "пишете",
          "3pl": "пишут"
        },
        "past": {
          "m": "писал",
          "f": "писала",
          "n": "писало",
          "pl": "писали"
        },
        "imperative": {
          "sg": "пиши",
          "pl": "пишите"
        }
      },
      "examples": [
        {
          "dst": "Я пишу письмо."
        },
        {
          "dst": "Он писал брату вечером."
        },
        {
          "dst": "Она писала подруге вчера."
        },
        {
          "dst": "Привидение писало письмо во сне."
        },
        {
          "dst": "Мы писали об этом вчера."
        },
        {
          "dst": "Я буду писать тебе чаще."
        },
        {
          "dst": "Пиши аккуратно."
        }
      ]
    },
    {
      "id": "ru_napisat",
      "rank": 18,
      "lemma": "написать",
      "morph": {
        "aspect": "perfective",
        "pair": "ru_pisat",
        "sem": "action"
      },
      "forms": {
        "present": {
          "1sg": "напишу",
          "2sg": "напишешь",
          "3sg": "напишет",
          "1pl": "напишем",
          "2pl": "напишете",
          "3pl": "напишут"
        },
        "past": {
          "m": "написал",
          "f": "написала",
          "n": "написало",
          "pl": "написали"
        },
        "imperative": {
          "sg": "напиши",
          "pl": "напишите"
        }
      },
      "examples": [
        {
          "dst": "Я напишу письмо вечером."
        },
        {
          "dst": "Он написал брату вчера."
        },
        {
          "dst": "Она написала подруге утром."
        },
        {
          "dst": "Это поколение написало новую страницу истории."
        },
        {
          "dst": "Мы написали об этом вчера."
        },
        {
          "dst": "Напиши мне завтра."
        }
      ]
    },
    {
      "id": "ru_chitat",
      "rank": 19,
      "lemma": "читать",
      "morph": {
        "aspect": "imperfective",
        "pair": "ru_prochitat",
        "sem": "action"
      },
      "forms": {
        "present": {
          "1sg": "читаю",
          "2sg": "читаешь",
          "3sg": "читает",
          "1pl": "читаем",
          "2pl": "читаете",
          "3pl": "читают"
        },
        "past": {
          "m": "читал",
          "f": "читала",
          "n": "читало",
          "pl": "читали"
        },
        "imperative": {
          "sg": "читай",
          "pl": "читайте"
        }
      },
      "examples": [
        {
          "dst": "Я читаю книгу."
        },
        {
          "dst": "Он читал письмо."
        },
        {
          "dst": "Она читала журнал."
        },
        {
          "dst": "Эхо читало строки в пустой комнате."
        },
        {
          "dst": "Мы читали это вчера."
        },
        {
          "dst": "Я буду читать вечером."
        },
        {
          "dst": "Читай внимательно."
        }
      ]
    },
    {
      "id": "ru_prochitat",
      "rank": 20,
      "lemma": "прочитать",
      "morph": {
        "aspect": "perfective",
        "pair": "ru_chitat",
        "sem": "action"
      },
      "forms": {
        "present": {
          "1sg": "прочитаю",
          "2sg": "прочитаешь",
          "3sg": "прочитает",
          "1pl": "прочитаем",
          "2pl": "прочитаете",
          "3pl": "прочитают"
        },
        "past": {
          "m": "прочитал",
          "f": "прочитала",
          "n": "прочитало",
          "pl": "прочитали"
        },
        "imperative": {
          "sg": "прочитай",
          "pl": "прочитайте"
        }
      },
      "examples": [
        {
          "dst": "Я прочитаю статью вечером."
        },
        {
          "dst": "Он прочитал письмо."
        },
        {
          "dst": "Она прочитала книгу."
        },
        {
          "dst": "Привидение прочитало письмо."
        },
        {
          "dst": "Мы прочитали текст."
        },
        {
          "dst": "Прочитай текст внимательно."
        }
      ]
    },
    {
      "id": "ru_smotret",
      "rank": 21,
      "lemma": "смотреть",
      "morph": {
        "aspect": "imperfective",
        "pair": "ru_posmotret",
        "sem": "mental"
      },
      "forms": {
        "present": {
          "1sg": "смотрю",
          "2sg": "смотришь",
          "3sg": "смотрит",
          "1pl": "смотрим",
          "2pl": "смотрите",
          "3pl": "смотрят"
        },
        "past": {
          "m": "смотрел",
          "f": "смотрела",
          "n": "смотрело",
          "pl": "смотрели"
        },
        "imperative": {
          "sg": "смотри",
          "pl": "смотрите"
        }
      },
      "examples": [
        {
          "dst": "Я смотрю в окно."
        },
        {
          "dst": "Он смотрел на море."
        },
        {
          "dst": "Она смотрела фильм вечером."
        },
        {
          "dst": "Это смотрело на нас из темноты."
        },
        {
          "dst": "Мы смотрели туда вчера."
        },
        {
          "dst": "Я буду смотреть этот сериал вечером."
        },
        {
          "dst": "Смотри внимательно."
        }
      ]
    },
    {
      "id": "ru_posmotret",
      "rank": 22,
      "lemma": "посмотреть",
      "morph": {
        "aspect": "perfective",
        "pair": "ru_smotret",
        "sem": "mental"
      },
      "forms": {
        "present": {
          "1sg": "посмотрю",
          "2sg": "посмотришь",
          "3sg": "посмотрит",
          "1pl": "посмотрим",
          "2pl": "посмотрите",
          "3pl": "посмотрят"
        },
        "past": {
          "m": "посмотрел",
          "f": "посмотрела",
          "n": "посмотрело",
          "pl": "посмотрели"
        },
        "imperative": {
          "sg": "посмотри",
          "pl": "посмотрите"
        }
      },
      "examples": [
        {
          "dst": "Я посмотрю фильм вечером."
        },
        {
          "dst": "Он посмотрел на часы."
        },
        {
          "dst": "Она посмотрела в окно."
        },
        {
          "dst": "Это посмотрело на нас из темноты."
        },
        {
          "dst": "Мы посмотрели этот дом вчера."
        },
        {
          "dst": "Посмотри сюда."
        }
      ]
    },
    {
      "id": "ru_otkryvat",
      "rank": 23,
      "lemma": "открывать",
      "morph": {
        "aspect": "imperfective",
        "pair": "ru_otkryt",
        "sem": "change"
      },
      "forms": {
        "present": {
          "1sg": "открываю",
          "2sg": "открываешь",
          "3sg": "открывает",
          "1pl": "открываем",
          "2pl": "открываете",
          "3pl": "открывают"
        },
        "past": {
          "m": "открывал",
          "f": "открывала",
          "n": "открывало",
          "pl": "открывали"
        },
        "imperative": {
          "sg": "открывай",
          "pl": "открывайте"
        }
      },
      "examples": [
        {
          "dst": "Я открываю окно."
        },
        {
          "dst": "Он открывал дверь утром."
        },
        {
          "dst": "Она открывала книгу медленно."
        },
        {
          "dst": "Это открывало новые возможности."
        },
        {
          "dst": "Мы открывали магазин рано."
        },
        {
          "dst": "Я буду открывать окно каждое утро."
        },
        {
          "dst": "Открывай дверь."
        }
      ]
    },
    {
      "id": "ru_otkryt",
      "rank": 24,
      "lemma": "открыть",
      "morph": {
        "aspect": "perfective",
        "pair": "ru_otkryvat",
        "sem": "change"
      },
      "forms": {
        "present": {
          "1sg": "открою",
          "2sg": "откроешь",
          "3sg": "откроет",
          "1pl": "откроем",
          "2pl": "откроете",
          "3pl": "откроют"
        },
        "past": {
          "m": "открыл",
          "f": "открыла",
          "n": "открыло",
          "pl": "открыли"
        },
        "imperative": {
          "sg": "открой",
          "pl": "откройте"
        }
      },
      "examples": [
        {
          "dst": "Я открою окно через минуту."
        },
        {
          "dst": "Он открыл дверь утром."
        },
        {
          "dst": "Она открыла книгу медленно."
        },
        {
          "dst": "Это открыло новые возможности."
        },
        {
          "dst": "Мы открыли магазин рано."
        },
        {
          "dst": "Открой дверь."
        }
      ]
    },
    {
      "id": "ru_zakryvat",
      "rank": 25,
      "lemma": "закрывать",
      "morph": {
        "aspect": "imperfective",
        "pair": "ru_zakryt",
        "sem": "change"
      },
      "forms": {
        "present": {
          "1sg": "закрываю",
          "2sg": "закрываешь",
          "3sg": "закрывает",
          "1pl": "закрываем",
          "2pl": "закрываете",
          "3pl": "закрывают"
        },
        "past": {
          "m": "закрывал",
          "f": "закрывала",
          "n": "закрывало",
          "pl": "закрывали"
        },
        "imperative": {
          "sg": "закрывай",
          "pl": "закрывайте"
        }
      },
      "examples": [
        {
          "dst": "Я закрываю окно."
        },
        {
          "dst": "Он закрывал дверь вечером."
        },
        {
          "dst": "Она закрывала книгу медленно."
        },
        {
          "dst": "Это закрывало нам путь."
        },
        {
          "dst": "Мы закрывали магазин поздно."
        },
        {
          "dst": "Я буду закрывать окно на ночь."
        },
        {
          "dst": "Закрывай дверь."
        }
      ]
    },
    {
      "id": "ru_zakryt",
      "rank": 26,
      "lemma": "закрыть",
      "morph": {
        "aspect": "perfective",
        "pair": "ru_zakryvat",
        "sem": "change"
      },
      "forms": {
        "present": {
          "1sg": "закрою",
          "2sg": "закроешь",
          "3sg": "закроет",
          "1pl": "закроем",
          "2pl": "закроете",
          "3pl": "закроют"
        },
        "past": {
          "m": "закрыл",
          "f": "закрыла",
          "n": "закрыло",
          "pl": "закрыли"
        },
        "imperative": {
          "sg": "закрой",
          "pl": "закройте"
        }
      },
      "examples": [
        {
          "dst": "Я закрою окно через минуту."
        },
        {
          "dst": "Он закрыл дверь вечером."
        },
        {
          "dst": "Она закрыла книгу медленно."
        },
        {
          "dst": "Это закрыло нам путь."
        },
        {
          "dst": "Мы закрыли магазин поздно."
        },
        {
          "dst": "Закрой дверь."
        }
      ]
    },
    {
      "id": "ru_pokupat",
      "rank": 27,
      "lemma": "покупать",
      "morph": {
        "aspect": "imperfective",
        "pair": "ru_kupit",
        "sem": "action"
      },
      "forms": {
        "present": {
          "1sg": "покупаю",
          "2sg": "покупаешь",
          "3sg": "покупает",
          "1pl": "покупаем",
          "2pl": "покупаете",
          "3pl": "покупают"
        },
        "past": {
          "m": "покупал",
          "f": "покупала",
          "n": "покупало",
          "pl": "покупали"
        },
        "imperative": {
          "sg": "покупай",
          "pl": "покупайте"
        }
      },
      "examples": [
        {
          "dst": "Я покупаю хлеб."
        },
        {
          "dst": "Он покупал билет утром."
        },
        {
          "dst": "Она покупала книгу вчера."
        },
        {
          "dst": "Это покупало нам немного времени."
        },
        {
          "dst": "Мы покупали продукты вечером."
        },
        {
          "dst": "Я буду покупать кофе по дороге."
        },
        {
          "dst": "Покупай свежий хлеб."
        }
      ]
    },
    {
      "id": "ru_kupit",
      "rank": 28,
      "lemma": "купить",
      "morph": {
        "aspect": "perfective",
        "pair": "ru_pokupat",
        "sem": "action"
      },
      "forms": {
        "present": {
          "1sg": "куплю",
          "2sg": "купишь",
          "3sg": "купит",
          "1pl": "купим",
          "2pl": "купите",
          "3pl": "купят"
        },
        "past": {
          "m": "купил",
          "f": "купила",
          "n": "купило",
          "pl": "купили"
        },
        "imperative": {
          "sg": "купи",
          "pl": "купите"
        }
      },
      "examples": [
        {
          "dst": "Я куплю билет завтра."
        },
        {
          "dst": "Он купил хлеб утром."
        },
        {
          "dst": "Она купила книгу вчера."
        },
        {
          "dst": "Это купило нам немного времени."
        },
        {
          "dst": "Мы купили продукты вечером."
        },
        {
          "dst": "Купи молоко."
        }
      ]
    },
    {
      "id": "ru_prodavat",
      "rank": 29,
      "lemma": "продавать",
      "morph": {
        "aspect": "imperfective",
        "pair": "ru_prodat",
        "sem": "action"
      },
      "forms": {
        "present": {
          "1sg": "продаю",
          "2sg": "продаёшь",
          "3sg": "продаёт",
          "1pl": "продаём",
          "2pl": "продаёте",
          "3pl": "продают"
        },
        "past": {
          "m": "продавал",
          "f": "продавала",
          "n": "продавало",
          "pl": "продавали"
        },
        "imperative": {
          "sg": "продавай",
          "pl": "продавайте"
        }
      },
      "examples": [
        {
          "dst": "Я продаю машину."
        },
        {
          "dst": "Он продавал книги на рынке."
        },
        {
          "dst": "Она продавала одежду онлайн."
        },
        {
          "dst": "Это продавало себя без рекламы."
        },
        {
          "dst": "Мы продавали овощи летом."
        },
        {
          "dst": "Я буду продавать старую мебель."
        },
        {
          "dst": "Продавай это дороже."
        }
      ]
    },
    {
      "id": "ru_prodat",
      "rank": 30,
      "lemma": "продать",
      "morph": {
        "aspect": "perfective",
        "pair": "ru_prodavat",
        "sem": "action"
      },
      "forms": {
        "present": {
          "1sg": "продам",
          "2sg": "продашь",
          "3sg": "продаст",
          "1pl": "продадим",
          "2pl": "продадите",
          "3pl": "продадут"
        },
        "past": {
          "m": "продал",
          "f": "продала",
          "n": "продало",
          "pl": "продали"
        },
        "imperative": {
          "sg": "продай",
          "pl": "продайте"
        }
      },
      "examples": [
        {
          "dst": "Я продам машину завтра."
        },
        {
          "dst": "Он продал книги на рынке."
        },
        {
          "dst": "Она продала одежду онлайн."
        },
        {
          "dst": "Это продало себя без рекламы."
        },
        {
          "dst": "Мы продали овощи утром."
        },
        {
          "dst": "Продай это дороже."
        }
      ]
    },
    {
      "id": "ru_sprashivat",
      "rank": 31,
      "lemma": "спрашивать",
      "morph": {
        "aspect": "imperfective",
        "pair": "ru_sprosit",
        "sem": "speech"
      },
      "forms": {
        "present": {
          "1sg": "спрашиваю",
          "2sg": "спрашиваешь",
          "3sg": "спрашивает",
          "1pl": "спрашиваем",
          "2pl": "спрашиваете",
          "3pl": "спрашивают"
        },
        "past": {
          "m": "спрашивал",
          "f": "спрашивала",
          "n": "спрашивало",
          "pl": "спрашивали"
        },
        "imperative": {
          "sg": "спрашивай",
          "pl": "спрашивайте"
        }
      },
      "examples": [
        {
          "dst": "Я спрашиваю об этом часто."
        },
        {
          "dst": "Он спрашивал учителя."
        },
        {
          "dst": "Она спрашивала дорогу."
        },
        {
          "dst": "Эхо спрашивало из темноты."
        },
        {
          "dst": "Мы спрашивали об этом вчера."
        },
        {
          "dst": "Я буду спрашивать у врача."
        },
        {
          "dst": "Спрашивай смелее."
        }
      ]
    },
    {
      "id": "ru_sprosit",
      "rank": 32,
      "lemma": "спросить",
      "morph": {
        "aspect": "perfective",
        "pair": "ru_sprashivat",
        "sem": "speech"
      },
      "forms": {
        "present": {
          "1sg": "спрошу",
          "2sg": "спросишь",
          "3sg": "спросит",
          "1pl": "спросим",
          "2pl": "спросите",
          "3pl": "спросят"
        },
        "past": {
          "m": "спросил",
          "f": "спросила",
          "n": "спросило",
          "pl": "спросили"
        },
        "imperative": {
          "sg": "спроси",
          "pl": "спросите"
        }
      },
      "examples": [
        {
          "dst": "Я спрошу об этом завтра."
        },
        {
          "dst": "Он спросил учителя."
        },
        {
          "dst": "Она спросила дорогу."
        },
        {
          "dst": "Привидение спросило одно слово."
        },
        {
          "dst": "Мы спросили об этом вчера."
        },
        {
          "dst": "Спроси его прямо."
        }
      ]
    },
    {
      "id": "ru_poluchat",
      "rank": 33,
      "lemma": "получать",
      "morph": {
        "aspect": "imperfective",
        "pair": "ru_poluchit",
        "sem": "action"
      },
      "forms": {
        "present": {
          "1sg": "получаю",
          "2sg": "получаешь",
          "3sg": "получает",
          "1pl": "получаем",
          "2pl": "получаете",
          "3pl": "получают"
        },
        "past": {
          "m": "получал",
          "f": "получала",
          "n": "получало",
          "pl": "получали"
        },
        "imperative": {
          "sg": "получай",
          "pl": "получайте"
        }
      },
      "examples": [
        {
          "dst": "Я получаю письма каждый день."
        },
        {
          "dst": "Он получал зарплату вовремя."
        },
        {
          "dst": "Она получала помощь от друзей."
        },
        {
          "dst": "Это получало слишком много внимания."
        },
        {
          "dst": "Мы получали ответы по почте."
        },
        {
          "dst": "Я буду получать новости по телефону."
        },
        {
          "dst": "Получай удовольствие от работы."
        }
      ]
    },
    {
      "id": "ru_poluchit",
      "rank": 34,
      "lemma": "получить",
      "morph": {
        "aspect": "perfective",
        "pair": "ru_poluchat",
        "sem": "action"
      },
      "forms": {
        "present": {
          "1sg": "получу",
          "2sg": "получишь",
          "3sg": "получит",
          "1pl": "получим",
          "2pl": "получите",
          "3pl": "получат"
        },
        "past": {
          "m": "получил",
          "f": "получила",
          "n": "получило",
          "pl": "получили"
        },
        "imperative": {
          "sg": "получи",
          "pl": "получите"
        }
      },
      "examples": [
        {
          "dst": "Я получу ответ завтра."
        },
        {
          "dst": "Он получил письмо утром."
        },
        {
          "dst": "Она получила помощь от друзей."
        },
        {
          "dst": "Это получило слишком много внимания."
        },
        {
          "dst": "Мы получили ответы по почте."
        },
        {
          "dst": "Получи разрешение заранее."
        }
      ]
    },
    {
      "id": "ru_prihodit",
      "rank": 35,
      "lemma": "приходить",
      "morph": {
        "aspect": "imperfective",
        "pair": "ru_priyti",
        "sem": "motion"
      },
      "forms": {
        "present": {
          "1sg": "прихожу",
          "2sg": "приходишь",
          "3sg": "приходит",
          "1pl": "приходим",
          "2pl": "приходите",
          "3pl": "приходят"
        },
        "past": {
          "m": "приходил",
          "f": "приходила",
          "n": "приходило",
          "pl": "приходили"
        },
        "imperative": {
          "sg": "приходи",
          "pl": "приходите"
        }
      },
      "examples": [
        {
          "dst": "Я прихожу домой поздно."
        },
        {
          "dst": "Он приходил рано утром."
        },
        {
          "dst": "Она приходила каждый день."
        },
        {
          "dst": "Это приходило неожиданно."
        },
        {
          "dst": "Мы приходили сюда летом."
        },
        {
          "dst": "Я буду приходить раньше."
        },
        {
          "dst": "Приходи завтра."
        }
      ]
    },
    {
      "id": "ru_priyti",
      "rank": 36,
      "lemma": "прийти",
      "morph": {
        "aspect": "perfective",
        "pair": "ru_prihodit",
        "sem": "motion"
      },
      "forms": {
        "present": {
          "1sg": "приду",
          "2sg": "придёшь",
          "3sg": "придёт",
          "1pl": "придём",
          "2pl": "придёте",
          "3pl": "придут"
        },
        "past": {
          "m": "пришёл",
          "f": "пришла",
          "n": "пришло",
          "pl": "пришли"
        },
        "imperative": {
          "sg": "приди",
          "pl": "придите"
        }
      },
      "examples": [
        {
          "dst": "Я приду завтра утром."
        },
        {
          "dst": "Он пришёл рано."
        },
        {
          "dst": "Она пришла вовремя."
        },
        {
          "dst": "Это пришло слишком поздно."
        },
        {
          "dst": "Мы пришли вместе."
        },
        {
          "dst": "Приди пораньше."
        }
      ]
    },
    {
      "id": "ru_nachinat",
      "rank": 37,
      "lemma": "начинать",
      "morph": {
        "aspect": "imperfective",
        "pair": "ru_nachat",
        "sem": "change"
      },
      "forms": {
        "present": {
          "1sg": "начинаю",
          "2sg": "начинаешь",
          "3sg": "начинает",
          "1pl": "начинаем",
          "2pl": "начинаете",
          "3pl": "начинают"
        },
        "past": {
          "m": "начинал",
          "f": "начинала",
          "n": "начинало",
          "pl": "начинали"
        },
        "imperative": {
          "sg": "начинай",
          "pl": "начинайте"
        }
      },
      "examples": [
        {
          "dst": "Я начинаю работу рано."
        },
        {
          "dst": "Он начинал медленно."
        },
        {
          "dst": "Она начинала с простого вопроса."
        },
        {
          "dst": "Это начинало новую эпоху."
        },
        {
          "dst": "Мы начинали в понедельник."
        },
        {
          "dst": "Я буду начинать раньше."
        },
        {
          "dst": "Начинай сейчас."
        }
      ]
    },
    {
      "id": "ru_nachat",
      "rank": 38,
      "lemma": "начать",
      "morph": {
        "aspect": "perfective",
        "pair": "ru_nachinat",
        "sem": "change"
      },
      "forms": {
        "present": {
          "1sg": "начну",
          "2sg": "начнёшь",
          "3sg": "начнёт",
          "1pl": "начнём",
          "2pl": "начнёте",
          "3pl": "начнут"
        },
        "past": {
          "m": "начал",
          "f": "начала",
          "n": "начало",
          "pl": "начали"
        },
        "imperative": {
          "sg": "начни",
          "pl": "начните"
        }
      },
      "examples": [
        {
          "dst": "Я начну работу утром."
        },
        {
          "dst": "Он начал медленно."
        },
        {
          "dst": "Она начала с простого вопроса."
        },
        {
          "dst": "Это начало новую эпоху."
        },
        {
          "dst": "Мы начали вовремя."
        },
        {
          "dst": "Начни сейчас."
        }
      ]
    },
    {
      "id": "ru_ponimat",
      "rank": 39,
      "lemma": "понимать",
      "morph": {
        "aspect": "imperfective",
        "pair": "ru_ponyat",
        "sem": "mental"
      },
      "forms": {
        "present": {
          "1sg": "понимаю",
          "2sg": "понимаешь",
          "3sg": "понимает",
          "1pl": "понимаем",
          "2pl": "понимаете",
          "3pl": "понимают"
        },
        "past": {
          "m": "понимал",
          "f": "понимала",
          "n": "понимало",
          "pl": "понимали"
        },
        "imperative": {
          "sg": "понимай",
          "pl": "понимайте"
        }
      },
      "examples": [
        {
          "dst": "Я понимаю этот вопрос."
        },
        {
          "dst": "Он понимал её слова."
        },
        {
          "dst": "Она понимала всё сразу."
        },
        {
          "dst": "Это общество понимало ситуацию."
        },
        {
          "dst": "Мы понимали друг друга."
        },
        {
          "dst": "Я буду понимать это лучше со временем."
        },
        {
          "dst": "Понимай меня правильно."
        }
      ]
    },
    {
      "id": "ru_ponyat",
      "rank": 40,
      "lemma": "понять",
      "morph": {
        "aspect": "perfective",
        "pair": "ru_ponimat",
        "sem": "mental"
      },
      "forms": {
        "present": {
          "1sg": "пойму",
          "2sg": "поймёшь",
          "3sg": "поймёт",
          "1pl": "поймём",
          "2pl": "поймёте",
          "3pl": "поймут"
        },
        "past": {
          "m": "понял",
          "f": "поняла",
          "n": "поняло",
          "pl": "поняли"
        },
        "imperative": {
          "sg": "пойми",
          "pl": "поймите"
        }
      },
      "examples": [
        {
          "dst": "Я пойму это позже."
        },
        {
          "dst": "Он понял её слова."
        },
        {
          "dst": "Она поняла всё сразу."
        },
        {
          "dst": "Это общество поняло ситуацию."
        },
        {
          "dst": "Мы поняли друг друга."
        },
        {
          "dst": "Пойми меня правильно."
        }
      ]
    }
  ]
}
